sidemail/__init__.py
sidemail/client.py
sidemail-0.1.2.dist-info/METADATA
sidemail-0.1.2.dist-info/WHEEL
sidemail-0.1.2.dist-info/top_level.txt
sidemail-0.1.2.dist-info/RECORD
