Metadata-Version: 2.4
Name: sidemail
Version: 0.1.2
Summary: Sidemail Python library for email sending and API
Author: Sidemail.io Development Team
License: MIT
Keywords: sidemail,email,api,client
Requires-Python: >=3.8
Requires-Dist: httpx>=0.24.0
Provides-Extra: dev
Requires-Dist: pytest; extra == "dev"
